{"axi":{"clock_period":5,"total_ticks":259},"dcma":{"clock_period":5,"total_ticks":259},"dma":{"clock_period":5,"total_ticks":259,"total_active":44,"any_active":44,"dma_count":2,"total_dma_ticks":518,"architecture_utilization":0.5,"algorithm_utilization":0.0849421},"vpro":{"clock_period":2.5,"total_ticks":516,"L0":{"any_active":200,"src_stall":0,"dst_stall":0,"architecture_utilization":1,"algorithm_utilization":0.387597,"src_stall_ratio":0,"dst_stall_ratio":0,"instructions":{"NONE":{"instructions":324,"cycles":324},"ADD":{"instructions":2,"cycles":128},"MACH":{"instructions":1,"cycles":64},"any":{"instructions":327,"cycles":516},"not_none":{"instructions":3,"cycles":192}}},"L1":{"any_active":0,"src_stall":0,"dst_stall":0,"architecture_utilization":nan,"algorithm_utilization":0,"src_stall_ratio":0,"dst_stall_ratio":0,"instructions":{"NONE":{"instructions":516,"cycles":516},"any":{"instructions":516,"cycles":516},"not_none":{"instructions":0,"cycles":0}}},"LS":{"any_active":232,"src_stall":20,"dst_stall":84,"architecture_utilization":1,"algorithm_utilization":0.399225,"src_stall_ratio":0.00968992,"dst_stall_ratio":0.0406977,"instructions":{"NONE":{"instructions":298,"cycles":324},"LOADS":{"instructions":2,"cycles":128},"STORE":{"instructions":1,"cycles":64},"any":{"instructions":301,"cycles":516},"not_none":{"instructions":3,"cycles":192}}}},"risc":{"clock_period":5,"total_ticks":259,"any_lane":116,"any_dma":44,"any_lane_or_dma":0,"eisv_cycles":259,"vpro_cycles":259,"vpro_busy":172}}